pypi_workflow/__init__.py
pypi_workflow/example.py
pypi_workflow-0.1.2.dist-info/LICENSE
pypi_workflow-0.1.2.dist-info/METADATA
pypi_workflow-0.1.2.dist-info/WHEEL
pypi_workflow-0.1.2.dist-info/RECORD
