Metadata-Version: 2.1
Name: pypi-workflow
Version: 0.1.2
Summary: Simple template for creating PyPI packages with automated publishing using GitHub Actions.
Home-page: https://github.com/SpaceShaman/pypi-workflow
License: MIT
Author: SpaceShaman
Author-email: spaceshaman@tuta.io
Requires-Python: >=3.10.0,<4.0.0
Classifier: License :: OSI Approved :: MIT License
Classifier: Programming Language :: Python :: 3
Classifier: Programming Language :: Python :: 3.10
Classifier: Programming Language :: Python :: 3.11
Classifier: Programming Language :: Python :: 3.12
Project-URL: Repository, https://github.com/SpaceShaman/pypi-workflow
